{
  "tradeId": "5dd67b0ca3da2a91",
  "week": 2,
  "season": "2025",
  "leagueId": "1235581944008286208",
  "participants": [
    "finthefiddle",
    "stevenbar24"
  ],
  "sides": [
    {
      "teamName": "finthefiddle",
      "teamContext": "Strong contender - win-now mode",
      "powerScore": {
        "powerScore": 88.9,
        "powerRank": 1,
        "lineupValueScore": 100,
        "performanceScore": 80.6,
        "positionalScore": 100,
        "depthScore": 52,
        "totalTeams": 16,
        "totalRosterValue": 43826
      },
      "tradeImpact": {
        "valueGained": 1043,
        "valueLost": 882,
        "netValueChange": 161,
        "estimatedPowerScoreChange": 0.2,
        "playersGained": [
          {
            "name": "Dallas Goedert",
            "value": 1043
          }
        ],
        "playersLost": [
          {
            "name": "Kyle Pitts",
            "value": 882
          }
        ]
      },
      "receives": [
        {
          "name": "Dallas Goedert",
          "position": "TE",
          "team": "PHI",
          "age": 30,
          "careerStage": "Prime Years"
        }
      ],
      "gives": [
        {
          "name": "Kyle Pitts",
          "position": "TE",
          "team": "ATL",
          "age": 25,
          "careerStage": "Entering Prime"
        }
      ]
    },
    {
      "teamName": "stevenbar24",
      "teamContext": "Playoff contender - competitive",
      "powerScore": {
        "powerScore": 65.6,
        "powerRank": 3,
        "lineupValueScore": 65,
        "performanceScore": 68.1,
        "positionalScore": 66.7,
        "depthScore": 44.8,
        "totalTeams": 16,
        "totalRosterValue": 28492
      },
      "tradeImpact": {
        "valueGained": 882,
        "valueLost": 1043,
        "netValueChange": -161,
        "estimatedPowerScoreChange": -0.2,
        "playersGained": [
          {
            "name": "Kyle Pitts",
            "value": 882
          }
        ],
        "playersLost": [
          {
            "name": "Dallas Goedert",
            "value": 1043
          }
        ]
      },
      "receives": [
        {
          "name": "Kyle Pitts",
          "position": "TE",
          "team": "ATL",
          "age": 25,
          "careerStage": "Entering Prime"
        }
      ],
      "gives": [
        {
          "name": "Dallas Goedert",
          "position": "TE",
          "team": "PHI",
          "age": 30,
          "careerStage": "Prime Years"
        }
      ]
    }
  ],
  "draftPicks": [],
  "persona": "Roy Keane",
  "analysis": "This is absolutely pointless. Week 2, both managers swapping tight ends who can't get you consistent points, and for what? There's no conviction here, no plan, no improvement for either side. It's like rearranging deck chairs on the Titanic.\n\nLet's be clear about what's happened: finthefiddle, sitting at 0-1 despite having the best power score in the league, has panicked after one week and swapped Kyle Pitts for Dallas Goedert. And he's supposed to be the winner here because the trade value says so? Rubbish. Goedert's projected for 1.1 points per game the rest of the way. 1.1! Pitts is projected for 1.4. Both are in run-heavy offenses, both disappear for weeks at a time, both are injury concerns. The only difference is Goedert's older and more banged up. Brilliant business that, trading for the worse player with a worse projection because some algorithm said he's worth more. This is the fantasy football equivalent of buying a 30-year-old midfielder when you already had a 25-year-old doing the same job.\n\nStevenbar24 isn't celebrating either. He's 1-0, sitting pretty, and he's just swapped one inconsistent tight end for another slightly worse one. At least Pitts has youth on his side—oh wait, that doesn't matter in redraft, does it? Kirk Cousins isn't going to suddenly start force-feeding him targets. The Falcons don't use their tight end properly, everyone knows it, and this manager's just bought into four years of disappointment hoping something changes. It won't. His trading history shows he barely makes moves—four trades all-time—and this is what he does when he finally pulls the trigger? Swapping sideways at a position that'll give you eight points one week and two the next? No ambition. No ruthlessness.\n\nThe timing is what kills me most. Week 2! You've got 13 weeks until the playoffs and these two are swapping deck chairs based on one game's worth of data. Finthefiddle's made 26 trades in his career—he's an active trader, always tinkering—but activity without purpose is just noise. This is change for change's sake. Neither manager has addressed their actual problems. Neither has improved their starting lineup in any meaningful way. The projected impact is 0.2 points up or down. Negligible. You know what that tells me? This trade shouldn't have been made at all. When you're making moves in Week 2, it should be because you've identified a clear weakness and you're attacking it. Not because you're bored and fancy a different name on your roster sheet. Absolute nonsense from both of them.",
  "generatedAt": "2025-12-31T00:32:37.537Z"
}